pygifconv_imfk/__init__.py
pygifconv_imfk/gif_converter.py
pygifconv_imfk-1.0.0.dist-info/LICENSE
pygifconv_imfk-1.0.0.dist-info/METADATA
pygifconv_imfk-1.0.0.dist-info/WHEEL
pygifconv_imfk-1.0.0.dist-info/top_level.txt
pygifconv_imfk-1.0.0.dist-info/RECORD
